db_migration_manager/__init__.py
db_migration_manager/py.typed
db_migration_manager/adapters/__init__.py
db_migration_manager/adapters/base.py
db_migration_manager/adapters/mysql.py
db_migration_manager/adapters/postgresql.py
db_migration_manager/adapters/sqlite.py
db_migration_manager/api/__init__.py
db_migration_manager/api/models.py
db_migration_manager/api/routes.py
db_migration_manager/cli/__init__.py
db_migration_manager/cli/__main__.py
db_migration_manager/cli/commands.py
db_migration_manager/core/__init__.py
db_migration_manager/core/manager.py
db_migration_manager/core/migration.py
db_migration_manager/core/models.py
db_migration_manager/core/pydantic_migration.py
db_migration_manager/core/schema.py
db_migration_manager-2.0.0.dist-info/METADATA
db_migration_manager-2.0.0.dist-info/WHEEL
db_migration_manager-2.0.0.dist-info/entry_points.txt
db_migration_manager-2.0.0.dist-info/top_level.txt
db_migration_manager-2.0.0.dist-info/RECORD
