Metadata-Version: 2.4
Name: db-migration-manager
Version: 2.0.0
Summary: A comprehensive, ORM-agnostic database migration system with FastAPI integration, supporting PostgreSQL, MySQL, and SQLite
Author-email: Ari Munandar <arimunandar.dev@gmail.com>
Project-URL: Homepage, https://github.com/arimunandar/db-migration-manager
Project-URL: Documentation, https://github.com/arimunandar/db-migration-manager#readme
Project-URL: Repository, https://github.com/arimunandar/db-migration-manager
Project-URL: Bug Tracker, https://github.com/arimunandar/db-migration-manager/issues
Project-URL: Changelog, https://github.com/arimunandar/db-migration-manager/blob/main/CHANGELOG.md
Keywords: database,migration,sql,postgresql,mysql,sqlite,fastapi,async,orm-agnostic
Classifier: Development Status :: 4 - Beta
Classifier: Intended Audience :: Developers
Classifier: Topic :: Database
Classifier: Topic :: Software Development :: Libraries :: Python Modules
Classifier: License :: OSI Approved :: MIT License
Classifier: Programming Language :: Python :: 3
Classifier: Programming Language :: Python :: 3.8
Classifier: Programming Language :: Python :: 3.9
Classifier: Programming Language :: Python :: 3.10
Classifier: Programming Language :: Python :: 3.11
Classifier: Programming Language :: Python :: 3.12
Requires-Python: >=3.8
Requires-Dist: click>=8.0.0
Requires-Dist: typing-extensions>=4.0.0; python_version < "3.10"
Requires-Dist: pydantic>=2.0.0
Provides-Extra: postgresql
Requires-Dist: asyncpg>=0.27.0; extra == "postgresql"
Provides-Extra: mysql
Requires-Dist: aiomysql>=0.1.1; extra == "mysql"
Provides-Extra: sqlite
Requires-Dist: aiosqlite>=0.17.0; extra == "sqlite"
Provides-Extra: fastapi
Requires-Dist: fastapi>=0.68.0; extra == "fastapi"
Requires-Dist: uvicorn[standard]>=0.15.0; extra == "fastapi"
Provides-Extra: pydantic
Requires-Dist: pydantic>=2.0.0; extra == "pydantic"
Provides-Extra: all
Requires-Dist: asyncpg>=0.27.0; extra == "all"
Requires-Dist: aiomysql>=0.1.1; extra == "all"
Requires-Dist: aiosqlite>=0.17.0; extra == "all"
Requires-Dist: fastapi>=0.68.0; extra == "all"
Requires-Dist: uvicorn[standard]>=0.15.0; extra == "all"
Requires-Dist: pydantic>=2.0.0; extra == "all"
Provides-Extra: dev
Requires-Dist: pytest>=7.0.0; extra == "dev"
Requires-Dist: pytest-asyncio>=0.21.0; extra == "dev"
Requires-Dist: pytest-cov>=4.0.0; extra == "dev"
Requires-Dist: black>=23.0.0; extra == "dev"
Requires-Dist: isort>=5.12.0; extra == "dev"
Requires-Dist: mypy>=1.0.0; extra == "dev"
Requires-Dist: flake8>=6.0.0; extra == "dev"
Requires-Dist: pre-commit>=3.0.0; extra == "dev"
Provides-Extra: test
Requires-Dist: pytest>=7.0.0; extra == "test"
Requires-Dist: pytest-asyncio>=0.21.0; extra == "test"
Requires-Dist: pytest-cov>=4.0.0; extra == "test"
Requires-Dist: aiosqlite>=0.17.0; extra == "test"
